djc_core_html_parser-1.0.3.dist-info/METADATA
djc_core_html_parser-1.0.3.dist-info/WHEEL
djc_core_html_parser-1.0.3.dist-info/licenses/LICENSE
djc_core_html_parser/__init__.py
djc_core_html_parser/__init__.pyi
djc_core_html_parser/djc_core_html_parser.cpython-313-s390x-linux-gnu.so
djc_core_html_parser/py.typed
djc_core_html_parser-1.0.3.dist-info/RECORD
