Metadata-Version: 2.4
Name: djc_core_html_parser
Version: 1.0.3
Classifier: Programming Language :: Python
Classifier: Programming Language :: Python :: 3
Classifier: Programming Language :: Python :: 3.8
Classifier: Programming Language :: Python :: 3.9
Classifier: Programming Language :: Python :: 3.10
Classifier: Programming Language :: Python :: 3.11
Classifier: Programming Language :: Python :: 3.12
Classifier: Programming Language :: Python :: 3.13
Classifier: Programming Language :: Python :: 3.14
Classifier: Programming Language :: Rust
Classifier: Programming Language :: Python :: Implementation :: CPython
Classifier: Programming Language :: Python :: Implementation :: PyPy
License-File: LICENSE
Summary: HTML parser used by django-components written in Rust.
Keywords: django,components,html
Author-email: Juro Oravec <juraj.oravec.josefson@gmail.com>
License: MIT
Requires-Python: >=3.8, <4.0
Project-URL: Homepage, https://github.com/django-components/djc-core-html-parser/
Project-URL: Changelog, https://github.com/django-components/djc-core-html-parser/blob/main/CHANGELOG.md
Project-URL: Issues, https://github.com/django-components/djc-core-html-parser/issues
Project-URL: Donate, https://github.com/sponsors/EmilStenstrom
